voxscriber/__init__.py
voxscriber/__main__.py
voxscriber/aligner.py
voxscriber/cli.py
voxscriber/diarizer.py
voxscriber/formatters.py
voxscriber/pipeline.py
voxscriber/preprocessor.py
voxscriber/transcriber.py
voxscriber-0.1.17.dist-info/METADATA
voxscriber-0.1.17.dist-info/WHEEL
voxscriber-0.1.17.dist-info/entry_points.txt
voxscriber-0.1.17.dist-info/licenses/LICENSE
voxscriber-0.1.17.dist-info/RECORD
