Metadata-Version: 2.4
Name: voxscriber
Version: 0.1.17
Summary: Local speaker diarization for Apple Silicon using MLX Whisper and Pyannote
Project-URL: Repository, https://github.com/dparedesi/voxscriber
Author: Daniel Paredes
License-Expression: MIT
License-File: LICENSE
Keywords: apple-silicon,mlx,pyannote,speaker-diarization,transcription,whisper
Classifier: Development Status :: 4 - Beta
Classifier: Environment :: Console
Classifier: Intended Audience :: Developers
Classifier: License :: OSI Approved :: MIT License
Classifier: Operating System :: MacOS
Classifier: Programming Language :: Python :: 3
Classifier: Programming Language :: Python :: 3.10
Classifier: Programming Language :: Python :: 3.11
Classifier: Programming Language :: Python :: 3.12
Classifier: Topic :: Multimedia :: Sound/Audio :: Speech
Requires-Python: >=3.10
Requires-Dist: mlx-whisper>=0.4.0
Requires-Dist: pyannote-audio>=3.1.0
Requires-Dist: pydub>=0.25.1
Requires-Dist: python-dotenv>=1.0.0
Requires-Dist: rich>=13.7.0
Requires-Dist: soundfile>=0.12.1
Requires-Dist: tqdm>=4.66.0
Provides-Extra: dev
Requires-Dist: pytest-mock>=3.10.0; extra == 'dev'
Requires-Dist: pytest>=7.0.0; extra == 'dev'
Requires-Dist: ruff>=0.1.0; extra == 'dev'
